[{"position":"1","points":"50","wins":"3","Driver":{"driverId":"nelson-piquet","code":"PIQ","givenName":"Nelson","familyName":"Piquet","nationality":"Brazil","url":"https://en.wikipedia.org/wiki/Nelson_Piquet_Souto_Maior","imageUrl":null},"Constructors":[]},{"position":"2","points":"49","wins":"2","Driver":{"driverId":"carlos-reutemann","code":"REU","givenName":"Carlos","familyName":"Reutemann","nationality":"Argentina","url":"https://en.wikipedia.org/wiki/Carlos_Alberto_Reutemann","imageUrl":null},"Constructors":[]},{"position":"3","points":"46","wins":"2","Driver":{"driverId":"alan-jones","code":"JON","givenName":"Alan","familyName":"Jones","nationality":"Australia","url":"https://en.wikipedia.org/wiki/Alan_Stanley_Jones","imageUrl":null},"Constructors":[]},{"position":"4","points":"44","wins":"2","Driver":{"driverId":"jacques-laffite","code":"LAF","givenName":"Jacques","familyName":"Laffite","nationality":"France","url":"https://en.wikipedia.org/wiki/Jacques-Henri_Laffite","imageUrl":null},"Constructors":[]},{"position":"5","points":"43","wins":"3","Driver":{"driverId":"alain-prost","code":"PRO","givenName":"Alain","familyName":"Prost","nationality":"France","url":"https://en.wikipedia.org/wiki/Alain_Marie_Pascal_Prost","imageUrl":null},"Constructors":[]},{"position":"6","points":"27","wins":"1","Driver":{"driverId":"john-watson","code":"WAT","givenName":"John","familyName":"Watson","nationality":"United Kingdom","url":"https://en.wikipedia.org/wiki/John_Marshall_Watson","imageUrl":null},"Constructors":[]},{"position":"7","points":"25","wins":"2","Driver":{"driverId":"gilles-villeneuve","code":"VIL","givenName":"Gilles","familyName":"Villeneuve","nationality":"Canada","url":"https://en.wikipedia.org/wiki/Joseph_Gilles_Henri_Villeneuve","imageUrl":null},"Constructors":[]},{"position":"8","points":"14","wins":"0","Driver":{"driverId":"elio-de-angelis","code":"DEA","givenName":"Elio","familyName":"De Angelis","nationality":"Italy","url":"https://en.wikipedia.org/wiki/Elio_de_Angelis","imageUrl":null},"Constructors":[]},{"position":"9","points":"11","wins":"0","Driver":{"driverId":"rene-arnoux","code":"ARN","givenName":"René","familyName":"Arnoux","nationality":"France","url":"https://en.wikipedia.org/wiki/Ren%C3%A9_Alexandre_Arnoux","imageUrl":null},"Constructors":[]},{"position":"10","points":"11","wins":"0","Driver":{"driverId":"hector-rebaque","code":"REB","givenName":"Héctor","familyName":"Rebaque","nationality":"Mexico","url":"https://en.wikipedia.org/wiki/H%C3%A9ctor_Alonso_Rebaque","imageUrl":null},"Constructors":[]},{"position":"11","points":"10","wins":"0","Driver":{"driverId":"riccardo-patrese","code":"PAT","givenName":"Riccardo","familyName":"Patrese","nationality":"Italy","url":"https://en.wikipedia.org/wiki/Riccardo_Gabriele_Patrese","imageUrl":null},"Constructors":[]},{"position":"12","points":"10","wins":"0","Driver":{"driverId":"eddie-cheever","code":"CHE","givenName":"Eddie","familyName":"Cheever","nationality":"United States of America","url":"https://en.wikipedia.org/wiki/Edward_McKay_Cheever_Jr.","imageUrl":null},"Constructors":[]},{"position":"13","points":"9","wins":"0","Driver":{"driverId":"didier-pironi","code":"PIR","givenName":"Didier","familyName":"Pironi","nationality":"France","url":"https://en.wikipedia.org/wiki/Didier_Joseph_Louis_Pironi","imageUrl":null},"Constructors":[]},{"position":"14","points":"8","wins":"0","Driver":{"driverId":"nigel-mansell","code":"MAN","givenName":"Nigel","familyName":"Mansell","nationality":"United Kingdom","url":"https://en.wikipedia.org/wiki/Nigel_Ernest_James_Mansell","imageUrl":null},"Constructors":[]},{"position":"15","points":"7","wins":"0","Driver":{"driverId":"bruno-giacomelli","code":"GIA","givenName":"Bruno","familyName":"Giacomelli","nationality":"Italy","url":"https://en.wikipedia.org/wiki/Bruno_Giacomelli","imageUrl":null},"Constructors":[]},{"position":"16","points":"4","wins":"0","Driver":{"driverId":"marc-surer","code":"SUR","givenName":"Marc","familyName":"Surer","nationality":"Switzerland","url":"https://en.wikipedia.org/wiki/Marc_Surer","imageUrl":null},"Constructors":[]},{"position":"17","points":"3","wins":"0","Driver":{"driverId":"mario-andretti","code":"AND","givenName":"Mario","familyName":"Andretti","nationality":"United States of America","url":"https://en.wikipedia.org/wiki/Mario_Gabriele_Andretti","imageUrl":null},"Constructors":[]},{"position":"18","points":"1","wins":"0","Driver":{"driverId":"patrick-tambay","code":"TAM","givenName":"Patrick","familyName":"Tambay","nationality":"France","url":"https://en.wikipedia.org/wiki/Patrick_Daniel_Tambay","imageUrl":null},"Constructors":[]},{"position":"18","points":"1","wins":"0","Driver":{"driverId":"andrea-de-cesaris","code":"DEC","givenName":"Andrea","familyName":"De Cesaris","nationality":"Italy","url":"https://en.wikipedia.org/wiki/Andrea_de_Cesaris","imageUrl":null},"Constructors":[]},{"position":"18","points":"1","wins":"0","Driver":{"driverId":"slim-borgudd","code":"BOR","givenName":"Slim","familyName":"Borgudd","nationality":"Sweden","url":"https://en.wikipedia.org/wiki/Karl_Edward_Tommy_Borgudd","imageUrl":null},"Constructors":[]},{"position":"18","points":"1","wins":"0","Driver":{"driverId":"eliseo-salazar","code":"SAL","givenName":"Eliseo","familyName":"Salazar","nationality":"Chile","url":"https://en.wikipedia.org/wiki/Eliseo_Salazar_Valenzuela","imageUrl":null},"Constructors":[]}]